ahmad_tik/__init__.py
ahmad_tik/my_class.py
ahmad_tik-0.0.1.dist-info/LICENSE
ahmad_tik-0.0.1.dist-info/METADATA
ahmad_tik-0.0.1.dist-info/WHEEL
ahmad_tik-0.0.1.dist-info/top_level.txt
ahmad_tik-0.0.1.dist-info/RECORD
