Metadata-Version: 2.1
Name: ahmad-tik
Version: 0.0.1
Summary: فحص يوزرات تيكتوك
Home-page: https://github.com/ahmad20l/ahmad-tik
Author: ahmad alenzi
Author-email: al-prns@hotmail.com
License: UNKNOWN
Project-URL: Bug Tracker, https://github.com/pypa/sampleproject/issues
Platform: UNKNOWN
Classifier: Programming Language :: Python :: 3
Classifier: License :: OSI Approved :: MIT License
Classifier: Operating System :: OS Independent
Requires-Python: >=3.6
License-File: LICENSE
